flu/__init__.py
flu/__main__.py
flu/colors.py
flu/flu.py
flu/hello.py
flu-0.0.4.dist-info/METADATA
flu-0.0.4.dist-info/WHEEL
flu-0.0.4.dist-info/entry_points.txt
flu-0.0.4.dist-info/top_level.txt
flu-0.0.4.dist-info/RECORD
