Metadata-Version: 2.1
Name: flu
Version: 0.0.4
Summary: CLI to generate beautiful & optimised website scaffolds
Home-page: https://github.com/strongSoda/flu
Author: Imran Khan
Author-email: ikhan77727@gmail.com
License: MIT
Platform: UNKNOWN
Classifier: License :: OSI Approved :: MIT License
Classifier: Programming Language :: Python :: 3
Classifier: Programming Language :: Python :: 3.7
Requires-Dist: Click
Requires-Dist: colorama
